{
  "winner": "player",
  "total_turns": 5,
  "final_player_hp": 321,
  "final_enemy_hp": -2,
  "player_name": "HERO",
  "enemy_name": "박쥐",
  "final_player_items": [
    "HP_S_potion",
    "HP_S_potion",
    "HP_M_potion",
    "MP_S_potion",
    "MP_S_potion"
  ],
  "logs": [
    {
      "turn": 1,
      "actor": "player",
      "action": "skill",
      "action_detail": "몸통박치기1",
      "damage_dealt": 26,
      "hp_after": 59,
      "mp_after": 17,
      "is_dodge": false,
      "is_crit": false,
      "debuff_applied": "",
      "escaped": false,
      "player_pt": 0.0,
      "enemy_pt": 0.0
    },
    {
      "turn": 1,
      "actor": "enemy",
      "action": "attack",
      "action_detail": "basic_attack",
      "damage_dealt": 9,
      "hp_after": 391,
      "mp_after": 34,
      "is_dodge": false,
      "is_crit": false,
      "debuff_applied": "",
      "escaped": false,
      "player_pt": 0.0,
      "enemy_pt": 0.0
    },
    {
      "turn": 2,
      "actor": "player",
      "action": "attack",
      "action_detail": "basic_attack",
      "damage_dealt": 15,
      "hp_after": 44,
      "mp_after": 17,
      "is_dodge": false,
      "is_crit": false,
      "debuff_applied": "",
      "escaped": false,
      "player_pt": 0.0,
      "enemy_pt": 0.0
    },
    {
      "turn": 2,
      "actor": "enemy",
      "action": "attack",
      "action_detail": "basic_attack",
      "damage_dealt": 14,
      "hp_after": 377,
      "mp_after": 34,
      "is_dodge": false,
      "is_crit": true,
      "debuff_applied": "",
      "escaped": false,
      "player_pt": 0.0,
      "enemy_pt": 0.0
    },
    {
      "turn": 3,
      "actor": "player",
      "action": "attack",
      "action_detail": "basic_attack",
      "damage_dealt": 15,
      "hp_after": 29,
      "mp_after": 17,
      "is_dodge": false,
      "is_crit": false,
      "debuff_applied": "",
      "escaped": false,
      "player_pt": 0.0,
      "enemy_pt": 0.0
    },
    {
      "turn": 3,
      "actor": "enemy",
      "action": "skill",
      "action_detail": "파이어볼1",
      "damage_dealt": 26,
      "hp_after": 351,
      "mp_after": 24,
      "is_dodge": false,
      "is_crit": false,
      "debuff_applied": "",
      "escaped": false,
      "player_pt": 0.0,
      "enemy_pt": 0.0
    },
    {
      "turn": 4,
      "actor": "player",
      "action": "attack",
      "action_detail": "basic_attack",
      "damage_dealt": 15,
      "hp_after": 14,
      "mp_after": 17,
      "is_dodge": false,
      "is_crit": false,
      "debuff_applied": "",
      "escaped": false,
      "player_pt": 0.0,
      "enemy_pt": 0.0
    },
    {
      "turn": 4,
      "actor": "enemy",
      "action": "skill",
      "action_detail": "파이어볼1",
      "damage_dealt": 30,
      "hp_after": 321,
      "mp_after": 14,
      "is_dodge": false,
      "is_crit": false,
      "debuff_applied": "",
      "escaped": false,
      "player_pt": 0.0,
      "enemy_pt": 0.0
    },
    {
      "turn": 5,
      "actor": "player",
      "action": "attack",
      "action_detail": "basic_attack",
      "damage_dealt": 16,
      "hp_after": 0,
      "mp_after": 17,
      "is_dodge": false,
      "is_crit": false,
      "debuff_applied": "",
      "escaped": false,
      "player_pt": 0.0,
      "enemy_pt": 0.0
    }
  ],
  "log_type": "player",
  "player_lv": 1,
  "timestamp": "20260501_180036",
  "items_used": []
}